openai_python_cache/__init__.py
openai_python_cache/api.py
openai_python_cache/provider.py
openai_python_cache-0.5.0.dist-info/LICENSE
openai_python_cache-0.5.0.dist-info/WHEEL
openai_python_cache-0.5.0.dist-info/METADATA
openai_python_cache-0.5.0.dist-info/RECORD
