Metadata-Version: 2.1
Name: openai-python-cache
Version: 0.5.0
Summary: A thin wrapper around the OpenAI Python bindings for caching responses.
Author: Ray Chen
Author-email: ray@raychen.io
Requires-Python: >=3.07,<4.0
Classifier: Programming Language :: Python :: 3
Classifier: Programming Language :: Python :: 3.7
Classifier: Programming Language :: Python :: 3.8
Classifier: Programming Language :: Python :: 3.9
Classifier: Programming Language :: Python :: 3.10
Classifier: Programming Language :: Python :: 3.11
Requires-Dist: openai (>=0.27.0,<0.28.0)
